ixload/IxLoadTestSettings.py
ixload/IxLoadUtils.py
ixload/IxRestPyUtils.py
ixload/IxRestUtils.py
ixload/__init__.py
ixload-0.0.13.dist-info/LICENSE
ixload-0.0.13.dist-info/METADATA
ixload-0.0.13.dist-info/WHEEL
ixload-0.0.13.dist-info/top_level.txt
ixload-0.0.13.dist-info/RECORD
