Metadata-Version: 2.1
Name: ixload
Version: 0.0.13
Summary: Python wrapper for IxLoad automation
Home-page: https://github.com/albertovillarreal-keys/ixload_py
Author: Alberto Villarreal
Author-email: alberto.villarreal@keysight.com
Classifier: Programming Language :: Python :: 3
Classifier: License :: OSI Approved :: MIT License
Classifier: Operating System :: OS Independent
Requires-Python: !=3.0.*,!=3.1.*,!=3.2.*,>=2.7
License-File: LICENSE
Requires-Dist: future
Requires-Dist: requests
